petepak/__init__.py
petepak/cli.py
petepak/listql.py
petepak/sorting.py
petepak-0.1.0.dist-info/licenses/LICENSE
petepak-0.1.0.dist-info/METADATA
petepak-0.1.0.dist-info/WHEEL
petepak-0.1.0.dist-info/entry_points.txt
petepak-0.1.0.dist-info/top_level.txt
petepak-0.1.0.dist-info/RECORD
